{
  "hash": "e8041bd6",
  "configHash": "b4694b7f",
  "lockfileHash": "7d671338",
  "browserHash": "b7824587",
  "optimized": {
    "easemob-websdk/uniApp/Easemob-chat": {
      "src": "../../../../../node_modules/easemob-websdk/uniApp/Easemob-chat.js",
      "file": "easemob-websdk_uniApp_Easemob-chat.js",
      "fileHash": "4ba47119",
      "needsInterop": true
    },
    "easemob-websdk/Easemob-chat": {
      "src": "../../../../../node_modules/easemob-websdk/Easemob-chat.js",
      "file": "easemob-websdk_Easemob-chat.js",
      "fileHash": "58f862ca",
      "needsInterop": true
    },
    "mobx": {
      "src": "../../../../../node_modules/mobx/dist/mobx.esm.js",
      "file": "mobx.js",
      "fileHash": "2b6d6b3c",
      "needsInterop": false
    },
    "pinyin-pro": {
      "src": "../../../../../node_modules/pinyin-pro/dist/index.mjs",
      "file": "pinyin-pro.js",
      "fileHash": "aff04257",
      "needsInterop": false
    }
  },
  "chunks": {
    "chunk-Y2F7D3TJ": {
      "file": "chunk-Y2F7D3TJ.js"
    }
  }
}